ansar/command/ansar_command.py
ansar/command/ansar_directory.py
ansar/command/ansar_group.py
ansar/command/shared_directory.py
ansar/connect/__init__.py
ansar/connect/connect_directory.py
ansar/connect/directory.py
ansar/connect/directory_if.py
ansar/connect/foh_if.py
ansar/connect/group_if.py
ansar/connect/grouping.py
ansar/connect/http.py
ansar/connect/moving.py
ansar/connect/networking.py
ansar/connect/networking_if.py
ansar/connect/node.py
ansar/connect/plumbing.py
ansar/connect/procedure.py
ansar/connect/product.py
ansar/connect/socketry.py
ansar/connect/standard.py
ansar/connect/transporting.py
ansar/connect/transporting_if.py
ansar/connect/wan.py
ansar_connect-1.1.54.dist-info/LICENSE
ansar_connect-1.1.54.dist-info/METADATA
ansar_connect-1.1.54.dist-info/WHEEL
ansar_connect-1.1.54.dist-info/entry_points.txt
ansar_connect-1.1.54.dist-info/top_level.txt
ansar_connect-1.1.54.dist-info/RECORD
