Metadata-Version: 2.2
Name: ansar-connect
Version: 1.1.54
Summary: Tools and runtime for network messaging
Author: Scott Woods
Author-email: Scott Woods <ansar.library.management@gmail.com>
Project-URL: Documentation, https://ansar-connect-manual.s3.ap-southeast-2.amazonaws.com/1.0.0/index.html
Classifier: Development Status :: 5 - Production/Stable
Classifier: Intended Audience :: Developers
Classifier: Programming Language :: Python :: 3
Classifier: Programming Language :: Python :: 3.7
Classifier: Programming Language :: Python :: 3.8
Classifier: Programming Language :: Python :: 3.9
Classifier: Programming Language :: Python :: 3.10
Classifier: Programming Language :: Python :: 3.11
Classifier: Programming Language :: Python :: 3.12
Classifier: License :: OSI Approved :: MIT License
Classifier: Operating System :: POSIX
Classifier: Operating System :: POSIX :: Linux
Classifier: Operating System :: POSIX :: BSD
Classifier: Operating System :: MacOS
Classifier: Topic :: Communications
Classifier: Topic :: Internet
Classifier: Topic :: Security :: Cryptography
Classifier: Topic :: Software Development
Classifier: Topic :: Software Development :: Libraries
Classifier: Topic :: Software Development :: Libraries :: Application Frameworks
Classifier: Topic :: System
Classifier: Topic :: System :: Networking
Classifier: Topic :: System :: Distributed Computing
Requires-Python: >=3.7
License-File: LICENSE
Requires-Dist: cffi>=1.16.0
Requires-Dist: PyNaCl>=1.5.0
Requires-Dist: ansar-create>=1.0.50
Dynamic: author
Dynamic: summary
